bdbf/__init__.py
bdbf/bdbf.py
bdbf/exceptions.py
bdbf/functions.py
bdbf/main.py
src/bdbf.py
bdbf-1.2.3.dist-info/LICENSE
bdbf-1.2.3.dist-info/METADATA
bdbf-1.2.3.dist-info/WHEEL
bdbf-1.2.3.dist-info/top_level.txt
bdbf-1.2.3.dist-info/RECORD
