Metadata-Version: 2.1
Name: bdbf
Version: 1.2.3
Summary: Bertik23's discord bot framework
Home-page: https://github.com/bertik23/bdbf
Author: Bertik23
Author-email: bertikxxiii@gmail.com
License: UNKNOWN
Keywords: discord,bot,framework
Platform: UNKNOWN
Classifier: Programming Language :: Python :: 3
Classifier: License :: OSI Approved :: MIT License
Classifier: Operating System :: OS Independent
Requires-Python: >=3.6
Requires-Dist: discord.py (>=1.4.1)
